dj_notebook/__init__.py
dj_notebook/config_helper.py
dj_notebook/shell_plus.py
dj_notebook-0.7.0.dist-info/LICENSE
dj_notebook-0.7.0.dist-info/METADATA
dj_notebook-0.7.0.dist-info/WHEEL
dj_notebook-0.7.0.dist-info/top_level.txt
dj_notebook-0.7.0.dist-info/RECORD
