Metadata-Version: 2.1
Name: dj_notebook
Version: 0.7.0
Summary: Django + shell_plus + Jupyter notebooks made easy
Author-email: Daniel Roy Greenfeld <daniel@feldroy.com>, Anna Zhydko <anna.zhydko@krakentechnologies.ltd>
Maintainer-email: Daniel Roy Greenfeld <daniel@feldroy.com>, Anna Zhydko <anna.zhydko@krakentechnologies.ltd>
License: GNU General Public License v3
Project-URL: bugs, https://github.com/pydanny/dj-notebook/issues
Project-URL: changelog, https://github.com/pydanny/dj-notebook/blob/master/CHANGELOG.md
Project-URL: homepage, https://github.com/pydanny/dj-notebook
Project-URL: documentation, https://dj-notebook.readthedocs.io/
Classifier: Development Status :: 5 - Production/Stable
Classifier: Framework :: Django :: 4.0
Classifier: Framework :: Django :: 4.1
Classifier: Framework :: Django :: 4.2
Classifier: Framework :: Django :: 5.0
Classifier: Framework :: Jupyter
Classifier: License :: OSI Approved :: GNU General Public License (GPL)
Classifier: Programming Language :: Python :: 3.10
Classifier: Programming Language :: Python :: 3.11
Classifier: Programming Language :: Python :: 3.12
License-File: LICENSE
Requires-Dist: django
Requires-Dist: django-extensions
Requires-Dist: django-pandas
Requires-Dist: django-schema-graph
Requires-Dist: ipython
Requires-Dist: jupyter
Requires-Dist: pandas
Requires-Dist: rich
Requires-Dist: python-dotenv
Provides-Extra: dev
Requires-Dist: black ; extra == 'dev'
Requires-Dist: black[jupyter] ; extra == 'dev'
Requires-Dist: coverage ; extra == 'dev'
Requires-Dist: griffe-typingdoc ==0.2.2 ; extra == 'dev'
Requires-Dist: mkdocs-material ; extra == 'dev'
Requires-Dist: mkdocs-jupyter ; extra == 'dev'
Requires-Dist: mkdocs-material[imaging] ; extra == 'dev'
Requires-Dist: mkdocs-include-markdown-plugin ; extra == 'dev'
Requires-Dist: mkdocstrings[python] >=0.18 ; extra == 'dev'
Requires-Dist: mypy ; extra == 'dev'
Requires-Dist: pytest ; extra == 'dev'
Requires-Dist: ruff ; extra == 'dev'
Requires-Dist: yamlfix ; extra == 'dev'
